setup.py
eks/__init__.py
eks/demo.py
eks/eks.py
eks/test.py
eks.egg-info/PKG-INFO
eks.egg-info/SOURCES.txt
eks.egg-info/dependency_links.txt
eks.egg-info/top_level.txt