Metadata-Version: 1.0
Name: eks
Version: 0.1.1
Summary: A Python library to communicate with an Euchner Electronic-Key-System (EKS).
Home-page: https://github.com/olisim/eks
Author: Jochen Breuer
Author-email: breuer@dajool.com
License: MIT
Keywords: eks Euchner Electronic Key System keysystem
Platform: any
